babelon/__init__.py
babelon/babelon_io.py
babelon/cli.py
babelon/constants.py
babelon/dataclasses.py
babelon/parsers/xliff.py
babelon/schema/babelon.yaml
babelon/translate.py
babelon/translation_profile.py
babelon/utils.py
babelon-0.3.4.dist-info/LICENSE
babelon-0.3.4.dist-info/METADATA
babelon-0.3.4.dist-info/WHEEL
babelon-0.3.4.dist-info/entry_points.txt
babelon-0.3.4.dist-info/RECORD
