Metadata-Version: 2.1
Name: babelon
Version: 0.3.4
Summary: babelon
License: MIT
Author: Vinicius de Souza
Author-email: souzadevinicius@gmail.com
Requires-Python: >=3.11,<4.0
Classifier: License :: OSI Approved :: MIT License
Classifier: Programming Language :: Python :: 3
Classifier: Programming Language :: Python :: 3.11
Classifier: Programming Language :: Python :: 3.12
Classifier: Programming Language :: Python :: 3.13
Provides-Extra: docs
Requires-Dist: click
Requires-Dist: curies (>=0.7.7)
Requires-Dist: deepl (>=1.20.0)
Requires-Dist: importlib-metadata (>=4.8.0)
Requires-Dist: jsonasobj2 (>=1.0.4)
Requires-Dist: linkml (>=1.7.4)
Requires-Dist: linkml-runtime (>=1.7.1)
Requires-Dist: llm (>=0.19.1)
Requires-Dist: oaklib (>=0.6.0)
Requires-Dist: pandas (>=2.0.2)
Requires-Dist: python-dotenv (>=1.0.1,<2.0.0)
Requires-Dist: rdflib (>=6.3.2)
Requires-Dist: sssom (>=0.4.4)
Requires-Dist: tabulate (>=0.9.0)
Requires-Dist: xmltodict (>=0.13.0)
